torchmdo/__init__.py
torchmdo/interp.py
torchmdo/model.py
torchmdo/utils.py
torchmdo/fea/__init__.py
torchmdo/fea/base.py
torchmdo/fea/beam.py
torchmdo/lifting_line/__init__.py
torchmdo/lifting_line/wing.py
torchmdo/optimize/__init__.py
torchmdo/optimize/input_output.py
torchmdo/optimize/optimizer.py
torchmdo-0.1.2.dist-info/LICENSE
torchmdo-0.1.2.dist-info/METADATA
torchmdo-0.1.2.dist-info/WHEEL
torchmdo-0.1.2.dist-info/top_level.txt
torchmdo-0.1.2.dist-info/zip-safe
torchmdo-0.1.2.dist-info/RECORD
